README.md
setup.py
Bconvertacceslib/__init__.py
Bconvertacceslib/data_manager.py
Bconvertacceslib/linda_data_manager.py
Bconvertacceslib/use_linda_data_manager.py
Bconvertacceslib.egg-info/PKG-INFO
Bconvertacceslib.egg-info/SOURCES.txt
Bconvertacceslib.egg-info/dependency_links.txt
Bconvertacceslib.egg-info/not-zip-safe
Bconvertacceslib.egg-info/requires.txt
Bconvertacceslib.egg-info/top_level.txt