Metadata-Version: 2.1
Name: Bconvertacceslib
Version: 0.0.1
Summary: This lib transform data to communicate with CommLib
Home-page: UNKNOWN
License: CC0 1.0 Universal
Platform: UNKNOWN
Classifier: Development Status :: 4 - Beta
Classifier: Programming Language :: Python :: 3
Requires-Python: >=3
